{"cost":21.596502712363094,"driver":{"balance":49.2550588686007,"name":"Uber Stephanie"},"location":{"start":"(80, 77)","end":"(54, 33)"},"completed":true,"user":{"balance":3.403497287636906,"name":"Alex Reeser"}}
{"cost":12.829115006141778,"driver":{"balance":0.0,"name":"Uber Alice"},"location":{"start":"(95, 32)","end":"(97, 68)"},"completed":false,"user":{"balance":10.0,"name":"Patrick Cook"}}
{"cost":18.19754848904345,"driver":{"balance":14.55803879123476,"name":"Uber Ashley"},"location":{"start":"(53, 18)","end":"(16, 10)"},"completed":true,"user":{"balance":31.80245151095655,"name":"Casey Cook"}}
{"cost":28.85156368716381,"driver":{"balance":23.08125094973105,"name":"Uber Eric"},"location":{"start":"(4, 6)","end":"(12, 99)"},"completed":true,"user":{"balance":1.1484363128361892,"name":"Taylor Gater"}}
{"cost":23.3747610470282,"driver":{"balance":0.0,"name":"Uber Jim"},"location":{"start":"(45, 23)","end":"(80, 66)"},"completed":false,"user":{"balance":20.0,"name":"Odiseo Jimenez"}}
{"cost":23.362019333476617,"driver":{"balance":18.689615466781294,"name":"Uber Alice"},"location":{"start":"(94, 21)","end":"(72, 89)"},"completed":true,"user":{"balance":1.637980666523383,"name":"Alex Reeser"}}
{"cost":28.216404729773494,"driver":{"balance":22.573123783818797,"name":"Uber Eric"},"location":{"start":"(96, 79)","end":"(42, 43)"},"completed":true,"user":{"balance":0.0,"name":"Patrick Cook"}}
{"cost":23.240491068014297,"driver":{"balance":18.59239285441144,"name":"Uber Sierra"},"location":{"start":"(8, 81)","end":"(33, 28)"},"completed":true,"user":{"balance":26.759508931985703,"name":"Casey Cook"}}
{"cost":33.149911200182245,"driver":{"balance":45.112321814557234,"name":"Uber Sierra"},"location":{"start":"(44, 1)","end":"(73, 77)"},"completed":true,"user":{"balance":0.0,"name":"Taylor Gater"}}
{"cost":30.605458936461552,"driver":{"balance":24.484367149169245,"name":"Uber Alice"},"location":{"start":"(83, 29)","end":"(13, 0)"},"completed":true,"user":{"balance":0.0,"name":"Odiseo Jimenez"}}
{"cost":15.851583706652008,"driver":{"balance":35.254390749140406,"name":"Uber Eric"},"location":{"start":"(19, 37)","end":"(38, 59)"},"completed":true,"user":{"balance":9.148416293347992,"name":"Alex Reeser"}}
{"cost":29.08332818612263,"driver":{"balance":23.266662548898104,"name":"Uber Alice"},"location":{"start":"(1, 61)","end":"(80, 18)"},"completed":true,"user":{"balance":0.0,"name":"Patrick Cook"}}
{"cost":19.777522829734412,"driver":{"balance":15.82201826378753,"name":"Uber Rob"},"location":{"start":"(75, 74)","end":"(89, 23)"},"completed":true,"user":{"balance":30.222477170265588,"name":"Casey Cook"}}
{"cost":27.756397451092568,"driver":{"balance":22.205117960874055,"name":"Uber Dylan"},"location":{"start":"(1, 74)","end":"(2, 9)"},"completed":true,"user":{"balance":2.2436025489074325,"name":"Taylor Gater"}}
{"cost":28.16365158387765,"driver":{"balance":38.35293953088966,"name":"Uber Rob"},"location":{"start":"(72, 54)","end":"(17, 34)"},"completed":true,"user":{"balance":0.0,"name":"Odiseo Jimenez"}}
{"cost":29.39145766735848,"driver":{"balance":23.513166133886784,"name":"Uber Eric"},"location":{"start":"(54, 85)","end":"(80, 14)"},"completed":true,"user":{"balance":0.0,"name":"Alex Reeser"}}
{"cost":35.27945952846682,"driver":{"balance":28.22356762277346,"name":"Uber Jim"},"location":{"start":"(61, 19)","end":"(77, 99)"},"completed":true,"user":{"balance":0.0,"name":"Patrick Cook"}}
{"cost":18.11402908742839,"driver":{"balance":14.491223269942711,"name":"Uber Dylan"},"location":{"start":"(35, 77)","end":"(69, 61)"},"completed":true,"user":{"balance":31.88597091257161,"name":"Casey Cook"}}
{"cost":20.516375052806158,"driver":{"balance":16.413100042244928,"name":"Uber Megan"},"location":{"start":"(39, 65)","end":"(45, 23)"},"completed":true,"user":{"balance":9.483624947193842,"name":"Taylor Gater"}}
{"cost":28.791076802170114,"driver":{"balance":23.03286144173609,"name":"Uber Stephanie"},"location":{"start":"(88, 45)","end":"(26, 88)"},"completed":true,"user":{"balance":0.0,"name":"Odiseo Jimenez"}}
{"cost":24.82072587709781,"driver":{"balance":19.85658070167825,"name":"Uber Rob"},"location":{"start":"(31, 50)","end":"(73, 9)"},"completed":true,"user":{"balance":0.17927412290218925,"name":"Alex Reeser"}}
